Metadata-Version: 2.1
Name: django-smart-models
Version: 0.2
Summary: Django smart models & fields with AI built-in
Home-page: https://github.com/manjumaigur/django-smart-models
Author: Manjunath Maigur
Author-email: manjumbmb97@gmail.com
License: UNKNOWN
Platform: UNKNOWN
Classifier: Environment :: Web Environment
Classifier: Framework :: Django
Classifier: Framework :: Django :: 4.1
Classifier: License :: OSI Approved :: MIT License
Classifier: Intended Audience :: Developers
Classifier: Operating System :: OS Independent
Classifier: Programming Language :: Python :: 3.9
Classifier: Topic :: Internet :: WWW/HTTP
Classifier: Topic :: Internet :: WWW/HTTP :: Dynamic Content
Requires-Python: >=3.9
License-File: LICENSE
